[
  {
    "image": "https://placedog.net/300",
    "name": "Lily",
    "owner": "Jazzy K.",
    "city": "Redlands"
  },
  {
    "image": "https://placedog.net/300",
    "name": "Remi",
    "owner": "Amanda S.",
    "city": "Topeka"
  },
  {
    "image": "https://placedog.net/300",
    "name": "Pepper",
    "owner": "Anthony M.",
    "city": "Dover"
  },
  {
    "image": "https://placedog.net/300",
    "name": "Abby",
    "owner": "John L.",
    "city": "Madison"
  },
  {
    "image": "https://placedog.net/300",
    "name": "Charlie",
    "owner": "Candice T.",
    "city": "Hutchinson"
  },
  {
    "image": "https://placedog.net/300",
    "name": "Allistair",
    "owner": "Justin A.",
    "city": "Bloomington"
  },
  {
    "image": "https://placedog.net/300",
    "name": "Damien",
    "owner": "Erica H.",
    "city": "Boston"
  },
  {
    "image": "https://placedog.net/300",
    "name": "Peanut",
    "owner": "Becky B.",
    "city": "Portland"
  },
  {
    "image": "https://placedog.net/300",
    "name": "Wesley",
    "owner": "Lee J",
    "city": "Vancouver"
  },
  {
    "image": "https://placedog.net/300",
    "name": "Cooper",
    "owner": "Zach P.",
    "city": "Bismark"
  }
]
